odoo/addons/iot_option_oca/README.rst
odoo/addons/iot_option_oca/__init__.py
odoo/addons/iot_option_oca/__manifest__.py
odoo/addons/iot_option_oca/i18n/es.po
odoo/addons/iot_option_oca/i18n/iot_option_oca.pot
odoo/addons/iot_option_oca/i18n/it.po
odoo/addons/iot_option_oca/models/__init__.py
odoo/addons/iot_option_oca/models/iot_device.py
odoo/addons/iot_option_oca/models/iot_device_input.py
odoo/addons/iot_option_oca/models/iot_device_property.py
odoo/addons/iot_option_oca/models/iot_template.py
odoo/addons/iot_option_oca/models/ir_actions_act_window_view.py
odoo/addons/iot_option_oca/models/ir_ui_view.py
odoo/addons/iot_option_oca/readme/CONTRIBUTORS.rst
odoo/addons/iot_option_oca/readme/DESCRIPTION.rst
odoo/addons/iot_option_oca/security/ir.model.access.csv
odoo/addons/iot_option_oca/static/description/icon.png
odoo/addons/iot_option_oca/static/description/index.html
odoo/addons/iot_option_oca/static/src/js/iot_option_renderer.js
odoo/addons/iot_option_oca/static/src/js/iot_option_view.js
odoo/addons/iot_option_oca/static/src/js/relational_fields.js
odoo/addons/iot_option_oca/static/src/scss/iot_option.scss
odoo/addons/iot_option_oca/static/src/xml/iot_option_item.xml
odoo/addons/iot_option_oca/tests/__init__.py
odoo/addons/iot_option_oca/tests/test_iot_template.py
odoo/addons/iot_option_oca/views/iot_device.xml
odoo/addons/iot_option_oca/views/iot_device_property.xml
odoo/addons/iot_option_oca/views/iot_template.xml
odoo_addon_iot_option_oca-15.0.1.0.0.11.dist-info/METADATA
odoo_addon_iot_option_oca-15.0.1.0.0.11.dist-info/WHEEL
odoo_addon_iot_option_oca-15.0.1.0.0.11.dist-info/top_level.txt
odoo_addon_iot_option_oca-15.0.1.0.0.11.dist-info/RECORD
